pyfireservicerota-0.0.46.dist-info/METADATA
pyfireservicerota-0.0.46.dist-info/WHEEL
pyfireservicerota-0.0.46.dist-info/entry_points.txt
pyfireservicerota-0.0.46.dist-info/licenses/LICENSE
pyfireservicerota/__init__.py
pyfireservicerota-0.0.46.dist-info/RECORD
