Metadata-Version: 2.1
Name: pyfireservicerota
Version: 0.0.46
Summary: Python 3 API wrapper for FireServiceRota/BrandweerRooster
Author-Email: Ron Klinkien <ron@cyberjunky.nl>
License: MIT
Classifier: Programming Language :: Python :: 3
Classifier: License :: OSI Approved :: MIT License
Classifier: Operating System :: OS Independent
Project-URL: Homepage, https://github.com/cyberjunky/python-fireservicerota
Project-URL: Bug Tracker, https://github.com/cyberjunky/python-fireservicerota/issues
Requires-Python: >=3.10
Requires-Dist: pytz
Requires-Dist: oauthlib
Requires-Dist: requests
Requires-Dist: websocket-client
